chemspec/__init__.py
chemspec/automl.py
chemspec/models.py
chemspec/preprocessing.py
chemspec-0.0.1.dist-info/LICENSE
chemspec-0.0.1.dist-info/METADATA
chemspec-0.0.1.dist-info/WHEEL
chemspec-0.0.1.dist-info/top_level.txt
chemspec-0.0.1.dist-info/RECORD
