Metadata-Version: 2.1
Name: chemspec
Version: 0.0.1
Summary: Chemometrics with spectroscopy
Author-email: Zefang Shen <zefang.zef.shen@gmail.com>
Maintainer-email: Zefang Shen <zefang.zef.shen@gmail.com>
Project-URL: Homepage, https://www.github.com
Project-URL: Documentation, https://www.github.com
Project-URL: Repository, https://www.github.com
Keywords: spectra,vis-NIR,IR,spectroscopy
Requires-Python: >=3.8
License-File: LICENSE
Requires-Dist: numpy
Requires-Dist: pandas
Requires-Dist: scipy
